{
  "realm": "otomeshon",
  "displayName": "Otomeshon Banking PoC",
  "enabled": true,
  "sslRequired": "external",
  "registrationAllowed": false,
  "loginWithEmailAllowed": true,
  "duplicateEmailsAllowed": false,
  "resetPasswordAllowed": true,
  "editUsernameAllowed": false,
  "bruteForceProtected": true,
  "permanentLockout": false,
  "maxFailureWaitSeconds": 900,
  "minimumQuickLoginWaitSeconds": 60,
  "waitIncrementSeconds": 60,
  "quickLoginCheckMilliSeconds": 1000,
  "maxDeltaTimeSeconds": 43200,
  "failureFactor": 30,
  
  "identityProviders": [
    {
      "alias": "google",
      "displayName": "Google",
      "providerId": "google",
      "enabled": true,
      "updateProfileFirstLoginMode": "on",
      "trustEmail": true,
      "storeToken": false,
      "addReadTokenRoleOnCreate": false,
      "authenticateByDefault": false,
      "linkOnly": false,
      "firstBrokerLoginFlowAlias": "first broker login",
      "config": {
        "clientId": "${env.GOOGLE_CLIENT_ID}",
        "clientSecret": "${env.GOOGLE_CLIENT_SECRET}",
        "hostedDomain": "${env.GOOGLE_HOSTED_DOMAIN:}",
        "userIp": "false",
        "offlineAccess": "false",
        "syncMode": "IMPORT"
      }
    },
    {
      "alias": "microsoft",
      "displayName": "Microsoft",
      "providerId": "microsoft",
      "enabled": true,
      "updateProfileFirstLoginMode": "on",
      "trustEmail": true,
      "storeToken": false,
      "addReadTokenRoleOnCreate": false,
      "authenticateByDefault": false,
      "linkOnly": false,
      "firstBrokerLoginFlowAlias": "first broker login",
      "config": {
        "clientId": "${env.MICROSOFT_CLIENT_ID}",
        "clientSecret": "${env.MICROSOFT_CLIENT_SECRET}",
        "tenant": "${env.MICROSOFT_TENANT_ID:common}",
        "syncMode": "IMPORT"
      }
    },
    {
      "alias": "azure-ad",
      "displayName": "Azure Active Directory",
      "providerId": "oidc",
      "enabled": true,
      "updateProfileFirstLoginMode": "on",
      "trustEmail": true,
      "storeToken": false,
      "addReadTokenRoleOnCreate": false,
      "authenticateByDefault": false,
      "linkOnly": false,
      "firstBrokerLoginFlowAlias": "first broker login",
      "config": {
        "clientId": "${env.AZURE_CLIENT_ID}",
        "clientSecret": "${env.AZURE_CLIENT_SECRET}",
        "authorizationUrl": "https://login.microsoftonline.com/${env.AZURE_TENANT_ID}/oauth2/v2.0/authorize",
        "tokenUrl": "https://login.microsoftonline.com/${env.AZURE_TENANT_ID}/oauth2/v2.0/token",
        "userInfoUrl": "https://graph.microsoft.com/oidc/userinfo",
        "jwksUrl": "https://login.microsoftonline.com/common/discovery/v2.0/keys",
        "issuer": "https://login.microsoftonline.com/${env.AZURE_TENANT_ID}/v2.0",
        "syncMode": "IMPORT",
        "clientAuthMethod": "client_secret_post"
      }
    }
  ],
  
  "identityProviderMappers": [
    {
      "name": "google-email-mapper",
      "identityProviderAlias": "google",
      "identityProviderMapper": "google-user-attribute-mapper",
      "config": {
        "syncMode": "INHERIT",
        "user.attribute": "email",
        "claim": "email"
      }
    },
    {
      "name": "google-name-mapper",
      "identityProviderAlias": "google",
      "identityProviderMapper": "google-user-attribute-mapper",
      "config": {
        "syncMode": "INHERIT",
        "user.attribute": "firstName",
        "claim": "given_name"
      }
    },
    {
      "name": "microsoft-email-mapper",
      "identityProviderAlias": "microsoft",
      "identityProviderMapper": "microsoft-user-attribute-mapper",
      "config": {
        "syncMode": "INHERIT",
        "user.attribute": "email",
        "claim": "email"
      }
    },
    {
      "name": "azure-department-mapper",
      "identityProviderAlias": "azure-ad",
      "identityProviderMapper": "oidc-user-attribute-idp-mapper",
      "config": {
        "syncMode": "INHERIT",
        "user.attribute": "department",
        "claim": "department"
      }
    }
  ],

  "clients": [
    {
      "clientId": "otomeshon-client",
      "name": "Otomeshon Banking Application",
      "description": "Main client for the Otomeshon banking PoC application",
      "enabled": true,
      "clientAuthenticatorType": "client-secret",
      "secret": "${env.KEYCLOAK_CLIENT_SECRET:otomeshon-secret}",
      "redirectUris": [
        "http://localhost:3000/*",
        "http://localhost:8000/*",
        "https://otomeshon.local/*"
      ],
      "webOrigins": [
        "http://localhost:3000",
        "http://localhost:8000",
        "https://otomeshon.local"
      ],
      "protocol": "openid-connect",
      "publicClient": false,
      "bearerOnly": false,
      "standardFlowEnabled": true,
      "implicitFlowEnabled": false,
      "directAccessGrantsEnabled": true,
      "serviceAccountsEnabled": true,
      "authorizationServicesEnabled": false,
      "fullScopeAllowed": true,
      "attributes": {
        "saml.assertion.signature": "false",
        "saml.force.post.binding": "false",
        "saml.multivalued.roles": "false",
        "saml.encrypt": "false",
        "saml.server.signature": "false",
        "saml.server.signature.keyinfo.ext": "false",
        "exclude.session.state.from.auth.response": "false",
        "saml_force_name_id_format": "false",
        "saml.client.signature": "false",
        "tls.client.certificate.bound.access.tokens": "false",
        "saml.authnstatement": "false",
        "display.on.consent.screen": "false",
        "saml.onetimeuse.condition": "false"
      },
      "protocolMappers": [
        {
          "name": "department",
          "protocol": "openid-connect",
          "protocolMapper": "oidc-usermodel-attribute-mapper",
          "consentRequired": false,
          "config": {
            "userinfo.token.claim": "true",
            "user.attribute": "department",
            "id.token.claim": "true",
            "access.token.claim": "true",
            "claim.name": "department",
            "jsonType.label": "String"
          }
        },
        {
          "name": "employee_id",
          "protocol": "openid-connect",
          "protocolMapper": "oidc-usermodel-attribute-mapper",
          "consentRequired": false,
          "config": {
            "userinfo.token.claim": "true",
            "user.attribute": "employee_id",
            "id.token.claim": "true",
            "access.token.claim": "true",
            "claim.name": "employee_id",
            "jsonType.label": "String"
          }
        },
        {
          "name": "business_unit",
          "protocol": "openid-connect",
          "protocolMapper": "oidc-usermodel-attribute-mapper",
          "consentRequired": false,
          "config": {
            "userinfo.token.claim": "true",
            "user.attribute": "business_unit",
            "id.token.claim": "true",
            "access.token.claim": "true",
            "claim.name": "business_unit",
            "jsonType.label": "String"
          }
        },
        {
          "name": "clearance_level",
          "protocol": "openid-connect",
          "protocolMapper": "oidc-usermodel-attribute-mapper",
          "consentRequired": false,
          "config": {
            "userinfo.token.claim": "true",
            "user.attribute": "clearance_level",
            "id.token.claim": "true",
            "access.token.claim": "true",
            "claim.name": "clearance_level",
            "jsonType.label": "String"
          }
        }
      ]
    }
  ],

  "roles": {
    "realm": [
      {
        "name": "admin",
        "description": "Administrator role with full system access"
      },
      {
        "name": "otomeshon-admin", 
        "description": "Otomeshon application administrator"
      },
      {
        "name": "trader",
        "description": "Basic trader role"
      },
      {
        "name": "senior-trader",
        "description": "Senior trader with elevated privileges"
      },
      {
        "name": "portfolio-manager",
        "description": "Portfolio manager role"
      },
      {
        "name": "operations-analyst",
        "description": "Operations analyst role"
      },
      {
        "name": "compliance-officer",
        "description": "Compliance officer role"
      },
      {
        "name": "risk-manager",
        "description": "Risk manager role"
      },
      {
        "name": "auditor",
        "description": "Internal auditor role"
      },
      {
        "name": "read-only",
        "description": "Read-only access to the system"
      }
    ]
  },

  "groups": [
    {
      "name": "Post-Trade Operations",
      "path": "/Post-Trade Operations",
      "realmRoles": ["operations-analyst"]
    },
    {
      "name": "Trading Desk",
      "path": "/Trading Desk", 
      "realmRoles": ["trader"]
    },
    {
      "name": "Risk Management",
      "path": "/Risk Management",
      "realmRoles": ["risk-manager"]
    },
    {
      "name": "Compliance",
      "path": "/Compliance",
      "realmRoles": ["compliance-officer"]
    },
    {
      "name": "Technology",
      "path": "/Technology",
      "realmRoles": ["admin"]
    }
  ],

  "browserSecurityHeaders": {
    "contentSecurityPolicyReportOnly": "",
    "xContentTypeOptions": "nosniff",
    "xRobotsTag": "none",
    "xFrameOptions": "SAMEORIGIN",
    "contentSecurityPolicy": "frame-src 'self'; frame-ancestors 'self'; object-src 'none';",
    "xXSSProtection": "1; mode=block",
    "strictTransportSecurity": "max-age=31536000; includeSubDomains"
  }
}